{"filename":"/Users/lucaalexandru/workspace/hermes/hermes-packages/database/hermes-packages.json","collections":[{"name":"migrations","data":[{"version":"1.0.0","description":"Add missing 'id' property","createdAt":"2019-07-12T15:37:29.647Z","id":"e7a00923-6da9-4206-be34-efb3245ed517","meta":{"revision":0,"created":1562945849648,"version":0},"$loki":1},{"version":"1.0.1","description":"Add 'jiraTaskKey' property to deployments with pull request meta","createdAt":"2019-07-12T15:37:29.648Z","id":"4093b913-d543-437c-9959-de47b1135626","meta":{"revision":0,"created":1562945849649,"version":0},"$loki":2},{"version":"1.0.2","description":"Save version denormalized","createdAt":"2019-07-12T15:37:29.649Z","id":"f5f7bd48-e7ac-4212-9b1c-1c4c32b90831","meta":{"revision":0,"created":1562945849649,"version":0},"$loki":3},{"version":"1.0.3","description":"Prune release deployments","createdAt":"2019-07-12T15:37:29.649Z","id":"b08162f9-15d1-49e0-afbf-78bf79941765","meta":{"revision":0,"created":1562945849649,"version":0},"$loki":4}],"idIndex":[1,2,3,4],"binaryIndices":{},"constraints":null,"uniqueNames":[],"transforms":{},"objType":"migrations","dirty":false,"cachedIndex":null,"cachedBinaryIndex":null,"cachedData":null,"adaptiveBinaryIndices":true,"transactional":false,"cloneObjects":true,"cloneMethod":"parse-stringify","asyncListeners":false,"disableMeta":false,"disableChangesApi":true,"disableDeltaChangesApi":true,"autoupdate":false,"serializableIndices":true,"ttl":null,"maxId":4,"DynamicViews":[],"events":{"insert":[],"update":[],"pre-insert":[],"pre-update":[],"close":[],"flushbuffer":[],"error":[],"delete":[null],"warning":[null]},"changes":[]},{"name":"deployments","data":[{"version":"1.0.0","pullRequestMeta":{"actualCommit":"d177b89aa167256de079e49b757df565d1ec6234","actualCommitAuthor":"alexandru.luca@hermes.com","actualCommitAuthorEmail":"alexandru.luca@hermes.com","pullDescription":"desc","pullId":"1","pullLink":"https://github.com/hermesMobile/hermes-function-offline-website/pull/1","pullTitle":"lambda test","sourceBranch":"feature/LBS-552","jiraTaskKey":"LBS-552","targetBranch":"develop","sha1":"sha1"},"band":"qa","isHotfix":false,"deployAsAwsLambdaFunction":true,"name":"hermes-function-offline-website","createdAt":"2019-07-12T15:37:58.462Z","id":"4e747324-9e6c-4fb3-9632-e566d7f231ae","meta":{"revision":18,"created":1562945878462,"version":0,"updated":1563188308299},"$loki":1,"updatedAt":"2019-07-15T10:58:28.299Z"},{"version":"1.0.0","band":"release","isHotfix":false,"deployAsAwsLambdaFunction":true,"name":"hermes-function-offline-website","createdAt":"2019-07-14T20:22:57.751Z","id":"f41d114f-b823-44fa-8d1b-8d5a53a87429","meta":{"revision":5,"created":1563135777752,"version":0,"updated":1563136311998},"$loki":2,"updatedAt":"2019-07-14T20:31:51.997Z","isProduction":true,"serverTags":["aluca-local-prod"]},{"version":"1.0.1","band":"release","isHotfix":false,"deployAsAwsLambdaFunction":true,"name":"hermes-function-offline-website","createdAt":"2019-07-14T20:22:57.751Z","id":"f41d114f-b823-44fa-8d1b-8d5a53a87429","meta":{"revision":5,"created":1563135777752,"version":0,"updated":1563136311998},"$loki":2,"updatedAt":"2019-07-14T20:31:51.997Z","isProduction":true,"serverTags":["aluca-local-prod"]},{"pullRequestMeta":{"status":"build-complete","actualCommit":"d177b89aa167256de079e49b757df565d1ec6234","actualCommitAuthor":"alexandru.luca@hermes.com","actualCommitAuthorEmail":"alexandru.luca@hermes.com","pullDescription":"desc","pullId":"1","pullLink":"https://github.com/hermesMobile/hermes-function-offline-website/pull/1","pullTitle":"lambda test","sourceBranch":"feature/LBS-552","jiraTaskKey":"LBS-552","targetBranch":"develop","sha1":"sha1"},"version":"5.1.233","iosCfBundleId":"280","androidVersionCode":"280","band":"qa","isHotfix":false,"name":"tag-test","isMobileApplicationDeployment":true,"createdAt":"2019-08-06T10:37:20.355Z","id":"978fc92c-7edb-4b69-8c6c-d0aeb6c7230f","meta":{"revision":1,"created":1565087840355,"version":0,"updated":1565087846561},"$loki":3,"updatedAt":"2019-08-06T10:37:26.560Z"},{"version":"5.1.233","iosCfBundleId":"280","androidVersionCode":"280","band":"release","isHotfix":false,"name":"tag-test","isMobileApplicationDeployment":true,"createdAt":"2019-08-06T10:47:42.121Z","id":"8368f035-5f57-4279-9348-c1cdce4024a7","meta":{"revision":0,"created":1565088462121,"version":0},"$loki":4},{"pullRequestMeta":{"status":"build-complete","actualCommit":"27deac367550108f21f7f5abf66ce10512ad0950","actualCommitAuthor":"luca.p.alexandru@gmail.com","actualCommitAuthorEmail":"luca.p.alexandru@gmail.com","pullDescription":"desc","pullId":"1","pullLink":"https://github.com/alexandruluca/pull-request-test/pull/2","pullTitle":"lambda test","sourceBranch":"feature/1","issueNumber":"1","targetBranch":"develop","sha1":"sha1"},"version":"1.0.0","band":"qa","isHotfix":false,"name":"pull-request-test","createdAt":"2019-12-22T14:49:18.055Z","id":"db7ecb07-fa39-4edf-9b30-327a8de6c60b","meta":{"revision":94,"created":1577026158056,"version":0,"updated":1577037745728},"$loki":5,"updatedAt":"2019-12-22T18:02:25.728Z"}],"idIndex":[1,2,2,3,4,5],"binaryIndices":{},"constraints":null,"uniqueNames":[],"transforms":{},"objType":"deployments","dirty":false,"cachedIndex":null,"cachedBinaryIndex":null,"cachedData":null,"adaptiveBinaryIndices":true,"transactional":false,"cloneObjects":true,"cloneMethod":"parse-stringify","asyncListeners":false,"disableMeta":false,"disableChangesApi":true,"disableDeltaChangesApi":true,"autoupdate":false,"serializableIndices":true,"ttl":null,"maxId":5,"DynamicViews":[],"events":{"insert":[],"update":[],"pre-insert":[],"pre-update":[],"close":[],"flushbuffer":[],"error":[],"delete":[null],"warning":[null]},"changes":[]},{"name":"deployment-sequence","data":[],"idIndex":[],"binaryIndices":{},"constraints":null,"uniqueNames":[],"transforms":{},"objType":"deployment-sequence","dirty":false,"cachedIndex":null,"cachedBinaryIndex":null,"cachedData":null,"adaptiveBinaryIndices":true,"transactional":false,"cloneObjects":true,"cloneMethod":"parse-stringify","asyncListeners":false,"disableMeta":false,"disableChangesApi":true,"disableDeltaChangesApi":true,"autoupdate":false,"serializableIndices":true,"ttl":null,"maxId":0,"DynamicViews":[],"events":{"insert":[],"update":[],"pre-insert":[],"pre-update":[],"close":[],"flushbuffer":[],"error":[],"delete":[null],"warning":[null]},"changes":[]},{"name":"lambda-function","data":[],"idIndex":[],"binaryIndices":{},"constraints":null,"uniqueNames":[],"transforms":{},"objType":"lambda-function","dirty":false,"cachedIndex":null,"cachedBinaryIndex":null,"cachedData":null,"adaptiveBinaryIndices":true,"transactional":false,"cloneObjects":true,"cloneMethod":"parse-stringify","asyncListeners":false,"disableMeta":false,"disableChangesApi":true,"disableDeltaChangesApi":true,"autoupdate":false,"serializableIndices":true,"ttl":null,"maxId":0,"DynamicViews":[],"events":{"insert":[],"update":[],"pre-insert":[],"pre-update":[],"close":[],"flushbuffer":[],"error":[],"delete":[null],"warning":[null]},"changes":[]},{"name":"lambda-function-version","data":[{"name":"hermes-function-offline-website","version":"9","alias":"aluca-local","deploymentVersion":"1.0.0","band":"qa","createdAt":"2019-07-14T19:06:38.150Z","id":"2183d45b-9ccd-4785-8afc-5efcfe4a9a0c","meta":{"revision":5,"created":1563131198151,"version":0,"updated":1563135827560},"$loki":1,"updatedAt":"2019-07-14T20:23:47.560Z"},{"name":"hermes-function-offline-website","version":"8","alias":"release","deploymentVersion":"1.0.0","band":"release","createdAt":"2019-07-14T19:34:44.392Z","id":"70d8987e-a7e9-4170-aea0-2e7196663e9d","meta":{"revision":1,"created":1563132884392,"version":0,"updated":1563135781040},"$loki":2,"updatedAt":"2019-07-14T20:23:01.040Z"},{"name":"hermes-function-offline-website","alias":"aluca-local-qa","deploymentVersion":"1.0.0","band":"qa","version":"11","createdAt":"2019-07-15T11:18:06.193Z","id":"f9b3c2ba-1f44-4077-89da-223697a91f91","meta":{"revision":0,"created":1563189486194,"version":0},"$loki":3}],"idIndex":[1,2,3],"binaryIndices":{},"constraints":null,"uniqueNames":[],"transforms":{},"objType":"lambda-function-version","dirty":false,"cachedIndex":null,"cachedBinaryIndex":null,"cachedData":null,"adaptiveBinaryIndices":true,"transactional":false,"cloneObjects":true,"cloneMethod":"parse-stringify","asyncListeners":false,"disableMeta":false,"disableChangesApi":true,"disableDeltaChangesApi":true,"autoupdate":false,"serializableIndices":true,"ttl":null,"maxId":3,"DynamicViews":[],"events":{"insert":[],"update":[],"pre-insert":[],"pre-update":[],"close":[],"flushbuffer":[],"error":[],"delete":[null],"warning":[null]},"changes":[]}],"databaseVersion":1.5,"engineVersion":1.5,"autosave":true,"autosaveInterval":500,"autosaveHandle":null,"throttledSaves":true,"options":{"clone":true,"autoload":true,"autosave":true,"autosaveInterval":500,"adapter":null,"serializationMethod":"normal","destructureDelimiter":"$<\n","recursiveWait":true,"recursiveWaitLimit":false,"recursiveWaitLimitDuration":2000,"started":1577037709692},"persistenceMethod":"fs","persistenceAdapter":null,"verbose":false,"events":{"init":[null],"loaded":[],"flushChanges":[],"close":[],"changes":[],"warning":[]},"ENV":"NODEJS"}